optimparallel.py
optimparallel-0.1.3.dist-info/LICENSE
optimparallel-0.1.3.dist-info/METADATA
optimparallel-0.1.3.dist-info/WHEEL
optimparallel-0.1.3.dist-info/top_level.txt
optimparallel-0.1.3.dist-info/RECORD
