Metadata-Version: 2.1
Name: optimparallel
Version: 0.1.3
Summary: A parallel version of the L-BFGS-B optimizer of scipy.optimize.minimize().
Home-page: https://github.com/florafauna/optimParallel-python
Author: Florian Gerber
Author-email: flora.fauna.gerber@gmail.com
Classifier: Development Status :: 3 - Alpha
Classifier: Programming Language :: Python :: 3.9
Classifier: Programming Language :: Python :: 3.10
Classifier: Programming Language :: Python :: 3.11
Classifier: Programming Language :: Python :: 3.12
Classifier: License :: OSI Approved :: GNU General Public License v3 (GPLv3)
Classifier: Operating System :: OS Independent
Classifier: Topic :: Scientific/Engineering :: Mathematics
License-File: LICENSE
Requires-Dist: scipy
Requires-Dist: numpy
Provides-Extra: dev
Requires-Dist: pytest ; extra == 'dev'
